ntfy_csv_reminders/__init__.py
ntfy_csv_reminders/__main__.py
ntfy_csv_reminders/ntfy_csv_reminders.py
ntfy_csv_reminders-0.1.14.dist-info/licenses/LICENSE
ntfy_csv_reminders-0.1.14.dist-info/METADATA
ntfy_csv_reminders-0.1.14.dist-info/WHEEL
ntfy_csv_reminders-0.1.14.dist-info/entry_points.txt
ntfy_csv_reminders-0.1.14.dist-info/top_level.txt
ntfy_csv_reminders-0.1.14.dist-info/RECORD
