Metadata-Version: 2.4
Name: ntfy-csv-reminders
Version: 0.1.14
Summary: Probabilistic daily reminders via ntfy from csv
Home-page: https://github.com/thiswillbeyourgithub/ntfy-csv-reminders
License: GPLv3
Keywords: ntfy.sh,reminders,csv,tool,memory,distraction,distracted,todo,list
Classifier: Programming Language :: Python :: 3
Classifier: License :: OSI Approved :: GNU General Public License v3 (GPLv3)
Classifier: Operating System :: OS Independent
Requires-Python: >=3.11
License-File: LICENSE
Requires-Dist: fire>=0.6.0
Requires-Dist: requests>=2.32.4
Requires-Dist: caldav-tasks-api>=1.6.0
Dynamic: classifier
Dynamic: description
Dynamic: description-content-type
Dynamic: home-page
Dynamic: keywords
Dynamic: license
Dynamic: license-file
Dynamic: requires-dist
Dynamic: requires-python
Dynamic: summary
